{
  "current_version": "3.1.4",
  "releases": [
    {
      "version": "3.1.4",
      "date": "2026-04-09",
      "title": "削除プロセスの一本化",
      "summary": "削除フローをゴミ箱経由に統一しました。見直し画面からの削除も即座の物理削除ではなくゴミ箱に移動するようになり、復元も可能になりました。",
      "changes": [
        "見直し画面からの削除を物理削除からゴミ箱への論理削除に変更（30日後に自動物理削除）",
        "ゴミ箱からの復元時、タスク・プロジェクト・サブタスクの種別を問わず一律で Inbox の未分類アイテムとして復元するよう変更",
        "復元時にタグ・ステータス・実施場所・所要時間・エネルギー・親プロジェクト紐づけ・計画情報をすべてクリア（タイトル・メモは保持）",
        "見直し画面の説明文を新しい削除フローに合わせて更新"
      ]
    },
    {
      "version": "3.1.3",
      "date": "2026-04-09",
      "title": "お問い合わせのスパム対策強化",
      "summary": "お問い合わせ送信にレート制限と本文の妥当性チェックを追加し、スパム送信や Gmail 通知の浪費から保護するようにしました。",
      "changes": [
        "お問い合わせ送信にレート制限を追加（同一ユーザー + IP で 1時間あたり 10 件まで）",
        "本文のスパム検出を追加（同じ文字が80%以上を占める、または文字種が3種以下のとき送信を拒否）",
        "バリデーション失敗・スパム判定はレート制限のカウント対象外とし、正規ユーザーの誤入力に優しい挙動に",
        "レート制限到達時とスパム判定時の専用エラーメッセージを追加"
      ]
    },
    {
      "version": "3.1.2",
      "date": "2026-04-09",
      "title": "お問い合わせ送信エラーの修正",
      "summary": "Google Apps Script Web App が返す 302 リダイレクトを追跡できず、お問い合わせが送信できなかった不具合を修正しました。",
      "changes": [
        "お問い合わせ送信時に Google Apps Script Web App の 302 リダイレクトを自動追跡するよう修正（httpx.AsyncClient の follow_redirects=True を明示）",
        "リグレッションテストを追加し、302 リダイレクトが正常に追跡されることを検証"
      ]
    },
    {
      "version": "3.1.1",
      "date": "2026-04-08",
      "title": "デプロイ不具合の修正",
      "summary": "v3.1.0 でお問い合わせ機能実装時に httpx ライブラリを本番依存に追加し忘れていたため、Render での起動に失敗していた問題を修正しました。",
      "changes": [
        "お問い合わせ機能で使用する httpx ライブラリを本番依存に追加し、デプロイ失敗を解消"
      ]
    },
    {
      "version": "3.1.0",
      "date": "2026-04-08",
      "title": "UX改善とお問い合わせ機能",
      "summary": "スマホでの快適性向上、実績の可視化強化、ユーザー自身によるデータ管理、開発者への直接フィードバックを可能にしました。",
      "changes": [
        "実績機能を刷新: Inbox追加数・完了数・完了率を表示",
        "お問い合わせ機能を実装: 種別/メール/内容をフォームから送信",
        "アカウント削除機能を追加: 設定画面から自分のデータを完全削除可能",
        "新規登録時にパスワード再発行不可の警告と同意チェックを追加",
        "Inboxから分類済みアイテムを除外し、未分類のみ表示するよう変更",
        "スマホ閲覧時の画面倍率が変わる問題を修正（iOSオートズーム抑止）",
        "明確化画面・スキップ/削除ボタンのレスポンシブ対応を強化",
        "ハンバーガーメニューで「Defrago」テキストが見切れる問題を修正",
        "ログイン画面から開発者の思いを削除しシンプル化（ヘルプ画面で参照可）"
      ]
    },
    {
      "version": "3.0.0",
      "date": "2026-04-07",
      "title": "Defrago へリブランディング",
      "summary": "アプリ名を「MindFlow」から「Defrago」に変更しました。「脳をデフラグして実行する」という製品コンセプトを直接表現する名称です。",
      "changes": [
        "アプリ名を Defrago に変更（旧: MindFlow）",
        "キャッチコピー: 「散らばった思考を、ひとつの流れに。」",
        "全UI表示・ドキュメント・設定ファイルを Defrago に統一",
        "URL を defrago.onrender.com に変更",
        "リポジトリ名を Defrago に変更",
        "機能・データ構造に変更はありません（v2.0.0 と互換）"
      ]
    },
    {
      "version": "2.0.0",
      "date": "2026-04-07",
      "title": "エッセンシャル思考に基づく大改修",
      "summary": "Inbox→Taskまでの時間を短縮し、本当に重要なものだけに集中できる設計に刷新しました。",
      "changes": [
        "明確化フェーズを4分類ボタンに刷新（Yes/No質問を廃止）",
        "委任・プロジェクト・即実行・タスクの4分類で迷わず即時分類",
        "Inbox入力時に直接分類できるショートカットボタンを追加",
        "明確化中のスキップ機能（Inboxに残して後で再分類）",
        "ゴミ箱機能を追加（削除後30日保持・復元可能・自動物理削除）",
        "整理フェーズと重要度×緊急度マトリクスを廃止",
        "カレンダータグを廃止し4分類体系に統一",
        "ダッシュボードを簡素化（マトリクス削除）",
        "プロジェクト計画ウィザード（6ステップ）は継続",
        "見直しフェーズからの削除は即時物理削除（その他はゴミ箱経由）",
        "マルチテナント対応・データ完全分離は維持"
      ]
    },
    {
      "version": "1.1.0",
      "date": "2026-04-06",
      "title": "マルチテナント・通知・設定機能の強化",
      "summary": "マルチテナント対応、通知システム、設定画面、バージョン管理機能を追加しました。",
      "changes": [
        "マルチテナント化: ユーザー登録・ログイン機能を追加し、ユーザーごとにデータを完全分離",
        "アイコンバー: 使い方・ヘルプ・受信ボックス・お問い合わせ・実績の5機能を全画面右上に配置",
        "通知システム: リリース情報の自動配信、実績達成通知、未読バッジ表示",
        "設定画面: 外観・通知設定・アプリ情報（バージョン表示）",
        "バージョン管理: releases.jsonによるリリースノート一元管理とアップデート情報ページ",
        "プロジェクト計画: GTDナチュラル・プランニング・モデルに基づく6ステップウィザード",
        "テキスト外部化: 全ユーザー向けテキストをlabels.jsonに集約（ハードコーディング排除）",
        "開発者情報: ヘルプ画面に開発者の思いと開発者ホームページへのリンクを追加",
        "インフラ改善: Neon Free PostgreSQLに移行しデータ永続化を実現",
        "セキュリティ強化: bcrypt暗号化、セッション固定攻撃防止、タイミング攻撃対策、CSPヘッダー"
      ]
    },
    {
      "version": "1.0.0",
      "date": "2026-04-05",
      "title": "MindFlow 正式リリース",
      "summary": "GTDベースのタスク管理アプリ「MindFlow」を正式リリースしました。",
      "changes": [
        "GTD 5フェーズ（収集・明確化・整理・実行・見直し）を完全サポート",
        "ナチュラル・プランニング・モデルによる6ステップのプロジェクト計画",
        "重要度×緊急度のアイゼンハワー・マトリクスによる優先順位可視化",
        "マルチユーザー対応（ユーザー登録・データ完全分離）",
        "bcryptによるパスワード暗号化・セッション認証",
        "モバイル・PC両対応のレスポンシブUI",
        "アイコンバー（使い方・ヘルプ・受信ボックス・お問い合わせ・実績）"
      ]
    }
  ]
}
